async_unzip/__init__.py
async_unzip/unzipper.py
async_unzip-0.3.6.dist-info/LICENSE
async_unzip-0.3.6.dist-info/METADATA
async_unzip-0.3.6.dist-info/WHEEL
async_unzip-0.3.6.dist-info/top_level.txt
async_unzip-0.3.6.dist-info/RECORD
