Metadata-Version: 2.1
Name: async-unzip
Version: 0.3.6
Summary: Async unzipping to prevent asyncio timeout errors and decrease the memory usage for bigger zip files
Home-page: https://github.com/ueni-ltd/async-unzip
Author: Dmytro Nikolayev
Author-email: dnikolayev@gmail.com
License: MIT
Keywords: async unzip
Classifier: Intended Audience :: Developers
Classifier: Environment :: Web Environment
Classifier: License :: OSI Approved :: MIT License
Classifier: Natural Language :: English
Classifier: Programming Language :: Python :: 3
Classifier: Programming Language :: Python :: 3.6
Classifier: Programming Language :: Python :: 3.7
Classifier: Programming Language :: Python :: 3.8
Classifier: Programming Language :: Python :: 3.9
Classifier: Programming Language :: Python :: 3.10
Classifier: Programming Language :: Python :: 3.11
Classifier: Topic :: Internet :: WWW/HTTP :: Dynamic Content
License-File: LICENSE
